pypoc/Order2OpenDX.py
pypoc/OrderAnalysis.py
pypoc/TopologyGroup.py
pypoc/__init__.py
pypoc/click.py
pypoc-0.0.1.dist-info/AUTHORS.rst
pypoc-0.0.1.dist-info/LICENSE
pypoc-0.0.1.dist-info/METADATA
pypoc-0.0.1.dist-info/WHEEL
pypoc-0.0.1.dist-info/entry_points.txt
pypoc-0.0.1.dist-info/top_level.txt
pypoc-0.0.1.dist-info/RECORD
