Metadata-Version: 2.1
Name: pypoc
Version: 0.0.1
Summary: Python package for analysis of molecular dynamics simulations of lipid membranes.
Home-page: https://github.com/alejogiley/pypoc
Author: Alejandro Gil-Ley
Author-email: alejogiley@gmail.com
License: MIT license
Keywords: pypoc
Platform: UNKNOWN
Classifier: Development Status :: 2 - Pre-Alpha
Classifier: Intended Audience :: Developers
Classifier: License :: OSI Approved :: MIT License
Classifier: Natural Language :: English
Classifier: Programming Language :: Python :: 3
Classifier: Programming Language :: Python :: 3.4
Classifier: Programming Language :: Python :: 3.5
Classifier: Programming Language :: Python :: 3.6
Classifier: Programming Language :: Python :: 3.7
Requires-Dist: Click (>=6.0)
Requires-Dist: numpy (>=1.16.0)
Requires-Dist: scipy (>=1.2.1)
Requires-Dist: mdanalysis
Requires-Dist: griddataformats
